rtl/cmos_inverter.v
// CMOS 1-bit Inverter 

module cmos_inverter(
  input in,
  output out 
);
  supply0 GND;
  supply1 PWR;

  pmos(out, PWR, in);
  nmos(out, GND, in);
endmodule

rtl/cmos_mux.v
// `include "cmos_inverter.v"

module cmos_mux(
  input i0,
  input i1,
  input s,
  output y 
);
  supply0 GND;
  supply1 PWR;

  wire s_bar;
  wire h, w1, w2, w3;

  cmos_inverter INV1(s, s_bar);
  cmos_inverter INV2(h, y);

  pmos(w1, PWR, s_bar);
  pmos(w1, PWR, i0);
  pmos(h, w1, s);
  pmos(h, w1, i1);
  nmos(h, w2, s_bar);
  nmos(w2, GND, i0);
  nmos(h, w3, s);
  nmos(w3, GND, i1);
endmodule

tb/cmos_mux_tb.v
`include "../rtl/cmos_mux.v"

module cmos_mux_tb();
  reg i0;
  reg i1;
  reg s;
  wire y;

  integer i;

  initial begin 
    $dumpfile("cmos_mux_tb.vcd");
    $dumpvars(0, cmos_mux_tb);

    i0 = 0;
    i1 = 0;
    s  = 0;
    for(i=0; i<8; i=i+1) begin
      #5;
      {s,i1,i0} = i;
    end
  end
  
  initial begin
    $display("s\t|i1\t|i0\t|y");
    $display("--------|-------|-------|-------");
    $monitor(s,"\t|",i1,"\t|",i0,"\t|",y);
    #40 $finish;
  end

  cmos_mux MUX(
    .i0(i0),
    .i1(i1),
    .s(s),
    .y(y)
  );
endmodule

tb/cmos_mux_tb.vcd
$date
	Sun Aug  1 21:57:22 2021
$end
$version
	Icarus Verilog
$end
$timescale
	1s
$end
$scope module cmos_mux_tb $end
$var wire 1 ! y $end
$var reg 1 " i0 $end
$var reg 1 # i1 $end
$var reg 1 $ s $end
$var integer 32 % i [31:0] $end
$scope module MUX $end
$var wire 1 & GND $end
$var wire 1 ' PWR $end
$var wire 1 ( h $end
$var wire 1 " i0 $end
$var wire 1 # i1 $end
$var wire 1 $ s $end
$var wire 1 ) s_bar $end
$var wire 1 * w1 $end
$var wire 1 + w2 $end
$var wire 1 , w3 $end
$var wire 1 ! y $end
$scope module INV1 $end
$var wire 1 - GND $end
$var wire 1 . PWR $end
$var wire 1 $ in $end
$var wire 1 ) out $end
$upscope $end
$scope module INV2 $end
$var wire 1 / GND $end
$var wire 1 0 PWR $end
$var wire 1 ( in $end
$var wire 1 ! out $end
$upscope $end
$upscope $end
$upscope $end
$enddefinitions $end
#0
$dumpvars
10
0/
1.
0-
z,
z+
1*
1)
1(
1'
0&
b0 %
0$
0#
0"
0!
$end
#5
b1 %
#10
b10 %
z*
1!
0(
0+
1"
#15
b11 %
0,
1#
1*
0!
1(
z+
0"
#20
b100 %
z*
1!
0(
0+
1"
#25
b101 %
0)
1$
z,
0#
1*
0!
1(
z+
0"
#30
b110 %
0+
1"
#35
b111 %
1!
0(
0,
1#
z+
0"
#40
b1000 %
0+
1"
