rtl/cmos_inverter.v
// CMOS 1-bit Inverter 

module cmos_inverter(
  input in,
  output out 
);
  supply0 GND;
  supply1 PWR;

  pmos(out, PWR, in);
  nmos(out, GND, in);
endmodule

rtl/cmos_mux.v
// `include "cmos_inverter.v"

module cmos_mux(
  input i0,
  input i1,
  input s,
  output y 
);
  supply0 GND;
  supply1 PWR;

  wire s_bar;
  wire h, w1, w2, w3;

  cmos_inverter INV1(s, s_bar);
  cmos_inverter INV2(h, y);

  pmos(w1, PWR, s_bar);
  pmos(w1, PWR, i0);
  pmos(h, w1, s);
  pmos(h, w1, i1);
  nmos(h, w2, s_bar);
  nmos(w2, GND, i0);
  nmos(h, w3, s);
  nmos(w3, GND, i1);
endmodule

rtl/cmos_xor_xnor.v
// `include "cmos_inverter.v"

module cmos_xor_xnor(
  input a,
  input b,
  output xor_o,
  output xnor_o
);
  supply0 GND;
  supply1 PWR;
  
  wire a_bar, b_bar;
  wire w1, w2;

  cmos_inverter INV1(a, a_bar);
  cmos_inverter INV2(b, b_bar);
  cmos_inverter INV3(w2, xor_o);

  pmos(w1, PWR, b);
  pmos(w1, PWR, a_bar);
  pmos(w2, w1, b_bar);
  pmos(w2, w1, a);
  nmos(w2, w3, b);
  nmos(w3, GND, a_bar);
  nmos(w2, w4, b_bar);
  nmos(w4, GND, a);

  assign xnor_o = w2;
endmodule

rtl/compressor3to2.v
// `include "../rtl/cmos_xor_xnor.v"
// `include "../rtl/cmos_mux.v"
// `include "../rtl/cmos_inverter.v"

module compressor3to2(
  input a0,
  input a1,
  input a2,
  output sout,
  output cout
);
  supply0 GND;
  supply1 PWR;

  cmos_xor_xnor XOR_XNOR(a0, a1, xo, xn);
  cmos_mux MUX(xo, xn, a2, sout);
  
  // carry logic 
  wire h, w1, w2, w3;

  pmos(w1, PWR, a0);
  pmos(w1, PWR, a1);
  pmos(h, w1, a2);
  pmos(h, w1, xo);
  nmos(h, w2, a0);
  nmos(w2, GND, a1);
  nmos(h, w3, a2);
  nmos(w3, GND, xo);

  cmos_inverter INV(h, cout);

endmodule

tb/compressor3to2_tb.v
`include "../rtl/compressor3to2.v"
`include "../rtl/cmos_xor_xnor.v"
`include "../rtl/cmos_mux.v"
// `include "../rtl/cmos_inverter.v"

module compressor3to2_tb();
  reg a0;
  reg a1;
  reg a2;
  wire sout;
  wire cout;

  integer i;

  initial begin 
    $dumpfile("compressor3to2_tb.vcd");
    $dumpvars(0, compressor3to2_tb);

    a0 = 0;
    a1 = 0;
    a2 = 0;
    for(i=0; i<8; i=i+1)
      #5 {a2,a1,a0} = i;
  end
  
  initial begin
    $display("a2\ta1\ta0\tsout\tcout");
    $monitor(a2,"\t",a1,"\t",a0,"\t",sout,"\t",cout);
    #40 $finish;
  end

  compressor3to2 CMP3to2(
    .a0(a0),
    .a1(a1),
    .a2(a2),
    .sout(sout),
    .cout(cout)
  );
endmodule

tb/compressor3to2_tb.vcd
$date
	Sun Aug  1 22:53:43 2021
$end
$version
	Icarus Verilog
$end
$timescale
	1s
$end
$scope module compressor3to2_tb $end
$var wire 1 ! cout $end
$var wire 1 " sout $end
$var reg 1 # a0 $end
$var reg 1 $ a1 $end
$var reg 1 % a2 $end
$var integer 32 & i [31:0] $end
$scope module CMP3to2 $end
$var wire 1 ' GND $end
$var wire 1 ( PWR $end
$var wire 1 # a0 $end
$var wire 1 $ a1 $end
$var wire 1 % a2 $end
$var wire 1 ! cout $end
$var wire 1 ) h $end
$var wire 1 " sout $end
$var wire 1 * w1 $end
$var wire 1 + w2 $end
$var wire 1 , w3 $end
$var wire 1 - xo $end
$var wire 1 . xn $end
$scope module INV $end
$var wire 1 / GND $end
$var wire 1 0 PWR $end
$var wire 1 ) in $end
$var wire 1 ! out $end
$upscope $end
$scope module MUX $end
$var wire 1 1 GND $end
$var wire 1 2 PWR $end
$var wire 1 3 h $end
$var wire 1 - i0 $end
$var wire 1 % s $end
$var wire 1 4 s_bar $end
$var wire 1 5 w1 $end
$var wire 1 6 w2 $end
$var wire 1 7 w3 $end
$var wire 1 " y $end
$var wire 1 . i1 $end
$scope module INV1 $end
$var wire 1 8 GND $end
$var wire 1 9 PWR $end
$var wire 1 % in $end
$var wire 1 4 out $end
$upscope $end
$scope module INV2 $end
$var wire 1 : GND $end
$var wire 1 ; PWR $end
$var wire 1 3 in $end
$var wire 1 " out $end
$upscope $end
$upscope $end
$scope module XOR_XNOR $end
$var wire 1 < GND $end
$var wire 1 = PWR $end
$var wire 1 # a $end
$var wire 1 > a_bar $end
$var wire 1 $ b $end
$var wire 1 ? b_bar $end
$var wire 1 @ w1 $end
$var wire 1 A w2 $end
$var wire 1 B w3 $end
$var wire 1 C w4 $end
$var wire 1 . xnor_o $end
$var wire 1 - xor_o $end
$scope module INV1 $end
$var wire 1 D GND $end
$var wire 1 E PWR $end
$var wire 1 # in $end
$var wire 1 > out $end
$upscope $end
$scope module INV2 $end
$var wire 1 F GND $end
$var wire 1 G PWR $end
$var wire 1 $ in $end
$var wire 1 ? out $end
$upscope $end
$scope module INV3 $end
$var wire 1 H GND $end
$var wire 1 I PWR $end
$var wire 1 A in $end
$var wire 1 - out $end
$upscope $end
$upscope $end
$upscope $end
$upscope $end
$enddefinitions $end
#0
$dumpvars
1I
0H
1G
0F
1E
0D
zC
0B
1A
1@
1?
1>
1=
0<
1;
0:
19
08
07
z6
15
14
13
12
01
10
0/
1.
0-
z,
z+
1*
1)
1(
0'
b0 &
0%
0$
0#
0"
0!
$end
#5
b1 &
#10
b10 &
z7
0.
0,
z5
1"
03
06
1-
0A
0C
zB
0>
1#
#15
b11 &
0+
z@
0?
1$
z7
0.
0,
z5
1"
03
06
1-
0A
zC
0B
1>
0#
#20
b100 &
z*
1!
0)
0C
1@
07
1.
z,
15
0"
13
z6
0-
1A
zB
0>
1#
#25
b101 &
04
1%
z+
1?
0$
1*
0!
1)
zC
1@
07
1.
z,
15
1"
03
z6
0-
1A
0B
1>
0#
#30
b110 &
z7
0"
13
0.
1!
0)
0,
06
1-
0A
0C
zB
0>
1#
#35
b111 &
0+
z@
0?
1$
z7
0"
13
0.
1!
0)
0,
06
1-
0A
zC
0B
1>
0#
#40
b1000 &
z*
0C
1@
07
1"
03
1.
1!
0)
z,
z6
0-
1A
zB
0>
1#
