rtl/cmos_inverter.v
// CMOS 1-bit Inverter 

module cmos_inverter(
  input in,
  output out 
);
  supply0 GND;
  supply1 PWR;

  pmos(out, PWR, in);
  nmos(out, GND, in);
endmodule

rtl/cmos_and.v
module cmos_and(
  input a1,
  input a2,
  output y
);
  supply0 GND;
  supply1 PWR;
  
  wire w1, w2;

  pmos(w1, PWR, a1);
  pmos(w1, PWR, a2);
  nmos(w1, w2, a1);
  nmos(w2, GND, a2);
  cmos_inverter INV(w1,y);
endmodule

rtl/cmos_xor_xnor.v
// `include "cmos_inverter.v"

module cmos_xor_xnor(
  input a,
  input b,
  output xor_o,
  output xnor_o
);
  supply0 GND;
  supply1 PWR;
  
  wire a_bar, b_bar;
  wire w1, w2;

  cmos_inverter INV1(a, a_bar);
  cmos_inverter INV2(b, b_bar);
  cmos_inverter INV3(w2, xor_o);

  pmos(w1, PWR, b);
  pmos(w1, PWR, a_bar);
  pmos(w2, w1, b_bar);
  pmos(w2, w1, a);
  nmos(w2, w3, b);
  nmos(w3, GND, a_bar);
  nmos(w2, w4, b_bar);
  nmos(w4, GND, a);

  assign xnor_o = w2;
endmodule

rtl/cmos_halfadder.v
// Half Adder

// `include "cmos_xor_xnor.v"
// `include "cmos_and.v"

module cmos_halfadder(
  input a,
  input b,
  output sum,
  output carry
);
  cmos_xor_xnor XOR_XNOR(a,b,sum,null);
  cmos_and AND(a,b,carry);
endmodule

rtl/mul2b.v
// `include "cmos_and.v"
// `include "cmos_halfadder.v"

module mul2b(
  input a0,
  input a1,
  input b0,
  input b1,
  output m0,
  output m1,
  output m2,
  output m3
);
  // Product Generation
  cmos_and AND0(a0,b0,w0);
  cmos_and AND1(a1,b0,w1);
  cmos_and AND2(a0,b1,w2);
  cmos_and AND3(a1,b1,w3);

  // Partial Addition
  cmos_halfadder HA1(w1,w2,ws1,wc1);

  // Final Addition
  cmos_halfadder HA2(wc1,w3,ws2,wc2);

  // Outputs
  assign m0 = w0;
  assign m1 = ws1;
  assign m2 = ws2;
  assign m3 = wc2;
endmodule

tb/mul2b_tb.v
`include "../rtl/mul2b.v"
`include "../rtl/cmos_and.v"
`include "../rtl/cmos_halfadder.v"
`include "../rtl/cmos_inverter.v"
`include "../rtl/cmos_xor_xnor.v"

module mul2b_tb();
  reg a0;
  reg a1;
  reg b0;
  reg b1;
  wire m0;
  wire m1;
  wire m2;
  wire m3;

  integer i;

  initial begin 
    $dumpfile("mul2b_tb.vcd");
    $dumpvars(0, mul2b_tb);

    a0 = 0;
    a1 = 0;
    b0 = 0;
    b1 = 0;
    for(i=0; i<16; i=i+1)
      #5 {a1,a0,b1,b0} = i;
  end
  
  initial begin
    $display("a1\ta0\tb1\tb0\tm3\tm2\tm1\tm0");
    $monitor(a1,"\t",a0,"\t",b1,"\t",b0,"\t",m3,"\t",m2,"\t",m1,"\t",m0);
    #80 $finish;
  end

  mul2b MUL(
    .a0(a0),
    .a1(a1),
    .b0(b0),
    .b1(b1),
    .m0(m0),
    .m1(m1),
    .m2(m2),
    .m3(m3)
  );
endmodule

tb/mul2b_tb.vcd
$date
	Tue Aug  3 22:31:09 2021
$end
$version
	Icarus Verilog
$end
$timescale
	1s
$end
$scope module mul2b_tb $end
$var wire 1 ! m3 $end
$var wire 1 " m2 $end
$var wire 1 # m1 $end
$var wire 1 $ m0 $end
$var reg 1 % a0 $end
$var reg 1 & a1 $end
$var reg 1 ' b0 $end
$var reg 1 ( b1 $end
$var integer 32 ) i [31:0] $end
$scope module MUL $end
$var wire 1 % a0 $end
$var wire 1 & a1 $end
$var wire 1 ' b0 $end
$var wire 1 ( b1 $end
$var wire 1 $ m0 $end
$var wire 1 # m1 $end
$var wire 1 " m2 $end
$var wire 1 ! m3 $end
$var wire 1 * w0 $end
$var wire 1 + w1 $end
$var wire 1 , w2 $end
$var wire 1 - w3 $end
$var wire 1 . wc1 $end
$var wire 1 / wc2 $end
$var wire 1 0 ws1 $end
$var wire 1 1 ws2 $end
$scope module AND0 $end
$var wire 1 2 GND $end
$var wire 1 3 PWR $end
$var wire 1 % a1 $end
$var wire 1 ' a2 $end
$var wire 1 4 w1 $end
$var wire 1 5 w2 $end
$var wire 1 * y $end
$scope module INV $end
$var wire 1 6 GND $end
$var wire 1 7 PWR $end
$var wire 1 4 in $end
$var wire 1 * out $end
$upscope $end
$upscope $end
$scope module AND1 $end
$var wire 1 8 GND $end
$var wire 1 9 PWR $end
$var wire 1 & a1 $end
$var wire 1 ' a2 $end
$var wire 1 : w1 $end
$var wire 1 ; w2 $end
$var wire 1 + y $end
$scope module INV $end
$var wire 1 < GND $end
$var wire 1 = PWR $end
$var wire 1 : in $end
$var wire 1 + out $end
$upscope $end
$upscope $end
$scope module AND2 $end
$var wire 1 > GND $end
$var wire 1 ? PWR $end
$var wire 1 % a1 $end
$var wire 1 ( a2 $end
$var wire 1 @ w1 $end
$var wire 1 A w2 $end
$var wire 1 , y $end
$scope module INV $end
$var wire 1 B GND $end
$var wire 1 C PWR $end
$var wire 1 @ in $end
$var wire 1 , out $end
$upscope $end
$upscope $end
$scope module AND3 $end
$var wire 1 D GND $end
$var wire 1 E PWR $end
$var wire 1 & a1 $end
$var wire 1 ( a2 $end
$var wire 1 F w1 $end
$var wire 1 G w2 $end
$var wire 1 - y $end
$scope module INV $end
$var wire 1 H GND $end
$var wire 1 I PWR $end
$var wire 1 F in $end
$var wire 1 - out $end
$upscope $end
$upscope $end
$scope module HA1 $end
$var wire 1 + a $end
$var wire 1 , b $end
$var wire 1 . carry $end
$var wire 1 0 sum $end
$var wire 1 J null $end
$scope module AND $end
$var wire 1 K GND $end
$var wire 1 L PWR $end
$var wire 1 + a1 $end
$var wire 1 , a2 $end
$var wire 1 M w1 $end
$var wire 1 N w2 $end
$var wire 1 . y $end
$scope module INV $end
$var wire 1 O GND $end
$var wire 1 P PWR $end
$var wire 1 M in $end
$var wire 1 . out $end
$upscope $end
$upscope $end
$scope module XOR_XNOR $end
$var wire 1 Q GND $end
$var wire 1 R PWR $end
$var wire 1 + a $end
$var wire 1 S a_bar $end
$var wire 1 , b $end
$var wire 1 T b_bar $end
$var wire 1 U w1 $end
$var wire 1 V w2 $end
$var wire 1 W w3 $end
$var wire 1 X w4 $end
$var wire 1 J xnor_o $end
$var wire 1 0 xor_o $end
$scope module INV1 $end
$var wire 1 Y GND $end
$var wire 1 Z PWR $end
$var wire 1 + in $end
$var wire 1 S out $end
$upscope $end
$scope module INV2 $end
$var wire 1 [ GND $end
$var wire 1 \ PWR $end
$var wire 1 , in $end
$var wire 1 T out $end
$upscope $end
$scope module INV3 $end
$var wire 1 ] GND $end
$var wire 1 ^ PWR $end
$var wire 1 V in $end
$var wire 1 0 out $end
$upscope $end
$upscope $end
$upscope $end
$scope module HA2 $end
$var wire 1 . a $end
$var wire 1 - b $end
$var wire 1 / carry $end
$var wire 1 1 sum $end
$var wire 1 _ null $end
$scope module AND $end
$var wire 1 ` GND $end
$var wire 1 a PWR $end
$var wire 1 . a1 $end
$var wire 1 - a2 $end
$var wire 1 b w1 $end
$var wire 1 c w2 $end
$var wire 1 / y $end
$scope module INV $end
$var wire 1 d GND $end
$var wire 1 e PWR $end
$var wire 1 b in $end
$var wire 1 / out $end
$upscope $end
$upscope $end
$scope module XOR_XNOR $end
$var wire 1 f GND $end
$var wire 1 g PWR $end
$var wire 1 . a $end
$var wire 1 h a_bar $end
$var wire 1 - b $end
$var wire 1 i b_bar $end
$var wire 1 j w1 $end
$var wire 1 k w2 $end
$var wire 1 l w3 $end
$var wire 1 m w4 $end
$var wire 1 _ xnor_o $end
$var wire 1 1 xor_o $end
$scope module INV1 $end
$var wire 1 n GND $end
$var wire 1 o PWR $end
$var wire 1 . in $end
$var wire 1 h out $end
$upscope $end
$scope module INV2 $end
$var wire 1 p GND $end
$var wire 1 q PWR $end
$var wire 1 - in $end
$var wire 1 i out $end
$upscope $end
$scope module INV3 $end
$var wire 1 r GND $end
$var wire 1 s PWR $end
$var wire 1 k in $end
$var wire 1 1 out $end
$upscope $end
$upscope $end
$upscope $end
$upscope $end
$upscope $end
$enddefinitions $end
#0
$dumpvars
1s
0r
1q
0p
1o
0n
zm
0l
1k
1j
1i
1h
1g
0f
1e
0d
zc
1b
1a
0`
1_
1^
0]
1\
0[
1Z
0Y
zX
0W
1V
1U
1T
1S
1R
0Q
1P
0O
zN
1M
1L
0K
1J
1I
0H
zG
1F
1E
0D
1C
0B
zA
1@
1?
0>
1=
0<
z;
1:
19
08
17
06
z5
14
13
02
01
00
0/
0.
0-
0,
0+
0*
b0 )
0(
0'
0&
0%
0$
0#
0"
0!
$end
#5
b1 )
#10
b10 )
05
0;
1'
#15
b11 )
0A
0G
1(
z5
z;
0'
#20
b100 )
05
0;
1'
#25
b101 )
1%
zA
zG
0(
z5
z;
0'
#30
b110 )
1$
1*
04
05
0;
1'
#35
b111 )
0N
zU
0J
1#
10
0V
0T
1,
0@
0A
0G
1(
0$
0*
14
z5
z;
0'
#40
b1000 )
1$
1*
04
05
0;
1'
#45
b1001 )
1&
0%
zN
1U
1J
0#
00
1V
1T
0,
1@
zA
zG
0(
0$
0*
14
z5
z;
0'
#50
b1010 )
05
0J
1#
10
0V
0X
zW
0S
1+
0:
0;
1'
#55
b1011 )
0A
0c
zj
0_
1"
11
0k
0i
1-
0F
0G
1(
z5
1J
0#
00
1V
zX
0W
1S
0+
1:
z;
0'
#60
b1100 )
05
0J
1#
10
0V
0X
zW
0S
1+
0:
0;
1'
#65
b1101 )
1%
zA
zc
1j
1_
0"
01
1k
1i
0-
1F
zG
0(
z5
1J
0#
00
1V
zX
0W
1S
0+
1:
z;
0'
#70
b1110 )
1$
1*
04
05
0J
1#
10
0V
0X
zW
0S
1+
0:
0;
1'
#75
b1111 )
0N
zU
0T
1,
0@
0A
0c
zj
0_
1"
11
0k
0i
1-
0F
0G
1(
0$
0*
14
z5
0J
1#
10
0V
zX
0W
1S
0+
1:
z;
0'
#80
b10000 )
1$
1*
04
05
1!
1/
0b
0m
1j
1_
0"
01
1k
zl
0h
1.
0M
0X
1U
1J
0#
00
1V
zW
0S
1+
0:
0;
1'
